README
haste.py
setup.py
haste.egg-info/PKG-INFO
haste.egg-info/SOURCES.txt
haste.egg-info/dependency_links.txt
haste.egg-info/entry_points.txt
haste.egg-info/requires.txt
haste.egg-info/top_level.txt