Metadata-Version: 1.0
Name: haste
Version: 0.6
Summary: Pure Python replacement of the hastebin.com client.
Home-page: http://www.cdf.utoronto.ca/~g8m/
Author: Devon Meunier
Author-email: devon.meunier@utoronto.ca
License: MIT
Platform: UNKNOWN
